{
    "main": [
        {
            "label": "women",
            "query": "women"
        },
        {
            "label": "men",
            "query": "men"
        }
    ],
    "secondary": {
        "men": [
            {
                "label": "New In",
                "query": "new-in"
            },
            {
                "label": "Clothing",
                "query": "clothing"
            },
            {
                "label": "Sportswear",
                "query": "sportswear"
            },
            {
                "label": "Jeans",
                "query": "jeans"
            },
            {
                "label": "Brands",
                "query": "brands"
            }
        ],
        "women": [
            {
                "label": "New In",
                "query": "new-in"
            },
            {
                "label": "Clothing",
                "query": "clothing"
            },
            {
                "label": "Dresses",
                "query": "dresses"
            },
            {
                "label": "Sportswear",
                "query": "sportswear"
            },
            {
                "label": "Jeans",
                "query": "jeans"
            },
            {
                "label": "Brands",
                "query": "brands"
            }
        ]
    },
    "nested": [
        {
            "label": "New In",
            "query": "new-in",
            "nestedNav": [
                {
                    "listType": "TEXT_ONLY",
                    "title": "new products",
                    "routes": {
                        "men": [
                            {
                                "label": "View All",
                                "query": "all"
                            },
                            {
                                "label": "Clothing",
                                "query": "clothing"
                            },
                            {
                                "label": "Shoes",
                                "query": "shoes"
                            },
                            {
                                "label": "Coats & Jackets",
                                "query": "coats,jackets"
                            },
                            {
                                "label": "Hoodies",
                                "query": "hoodies"
                            },
                            {
                                "label": "T-Shirt & Vests",
                                "query": "t-shirts,vests"
                            },
                            {
                                "label": "Sportswear",
                                "query": "sportswear"
                            }
                        ],
                        "women": [
                            {
                                "label": "View All",
                                "query": "all"
                            },
                            {
                                "label": "Clothing",
                                "query": "clothing"
                            },
                            {
                                "label": "Shoes",
                                "query": "shoes"
                            },
                            {
                                "label": "Dresses",
                                "query": "dresses"
                            },
                            {
                                "label": "Coats & Jackets",
                                "query": "coats,jackets"
                            },
                            {
                                "label": "Tops",
                                "query": "tops"
                            },
                            {
                                "label": "Sportswear",
                                "query": "sportswear"
                            }
                        ]
                    }
                },
                {
                    "listType": "ROUNDED_FIG_X",
                    "title": "brand drops",
                    "routes": {
                        "men": [
                            {
                                "fig": "/assets/nav/men/men-asos-design__new-in.webp",
                                "label": "ASOS DESIGN",
                                "query": "asos"
                            },
                            {
                                "fig": "/assets/nav/men/men-adidas__new-in.webp",
                                "label": "Adidas",
                                "query": "adidas"
                            },
                            {
                                "fig": "/assets/nav/men/men-new-balance__new-in.webp",
                                "label": "New Balance",
                                "query": "new balance"
                            },
                            {
                                "fig": "/assets/nav/men/men-nike__new-in.webp",
                                "label": "Nike",
                                "query": "nike"
                            },
                            {
                                "fig": "/assets/nav/men/men-jack-and-jones__new-in.webp",
                                "label": "Jack & Jones",
                                "query": "jack_jones"
                            },
                            {
                                "fig": "/assets/nav/men/men-the-north-face__new-in.webp",
                                "label": "The North Face",
                                "query": "the north face"
                            }
                        ],
                        "women": [
                            {
                                "fig": "/assets/nav/women/women-new-in__holiday.webp",
                                "label": "Holiday",
                                "query": "holiday"
                            },
                            {
                                "fig": "/assets/nav/women/women-new-in__the-essentials.webp",
                                "label": "The Essentials",
                                "query": "the-essentials"
                            },
                            {
                                "fig": "/assets/nav/women/women-new-in__wedding-guest.webp",
                                "label": "Wedding Guest",
                                "query": "wedding-guest"
                            },
                            {
                                "fig": "/assets/nav/women/women-new-in__adidas.webp",
                                "label": "Adidas",
                                "query": "adidas"
                            },
                            {
                                "fig": "/assets/nav/women/women-new-in__nike.webp",
                                "label": "Nike",
                                "query": "nike"
                            },
                            {
                                "fig": "/assets/nav/women/women-new-in__stradovarius.webp",
                                "label": "Stradivarius",
                                "query": "stradivarius"
                            }
                        ]
                    }
                },
                {
                    "listType": "ROUNDED_FIG_Y",
                    "title": "top saved",
                    "routes": {
                        "men": [
                            {
                                "fig": "/assets/nav/men/men-clothing__new-in.webp",
                                "label": "Clothing",
                                "query": "clothing"
                            },
                            {
                                "fig": "/assets/nav/men/men-brands__new-in.webp",
                                "label": "Brands",
                                "query": "brands"
                            },
                            {
                                "fig": "/assets/nav/men/men-sportwear__new-in.webp",
                                "label": "Sportswear",
                                "query": "sportswear"
                            },
                            {
                                "fig": "/assets/nav/men/men-trainers__new-in.webp",
                                "label": "Trainers",
                                "query": "trainers"
                            }
                        ],
                        "women": [
                            {
                                "fig": "/assets/nav/women/women-new-in__clothing.webp",
                                "label": "Clothing",
                                "query": "clothing"
                            },
                            {
                                "fig": "/assets/nav/women/women-new-in__brands.webp",
                                "label": "Brands",
                                "query": "brands"
                            },
                            {
                                "fig": "/assets/nav/women/women-new-in__trainers.webp",
                                "label": "Trainers",
                                "query": "trainers"
                            }
                        ]
                    }
                },
                {
                    "listType": "FIG_ONLY",
                    "title": "new edits",
                    "routes": {
                        "men": [
                            {
                                "fig": "/assets/nav/men/men-going-grunge__new-in.webp",
                                "label": "Going Grunge",
                                "query": "grunge"
                            },
                            {
                                "fig": "/assets/nav/men/men-wedding-attire__new-in.webp",
                                "label": "Wedding Attire",
                                "query": "wedding"
                            }
                        ],
                        "women": [
                            {
                                "fig": "/assets/nav/women/women-new-in__top-shop-denim.webp",
                                "label": "Topshop Denim",
                                "query": "topshop"
                            },
                            {
                                "fig": "/assets/nav/women/women-new-in__denim-weekend-collective.webp",
                                "label": "Denim Weekend Collective",
                                "query": "jeans"
                            }
                        ]
                    }
                }
            ]
        },
        {
            "label": "Clothing",
            "query": "clothing",
            "nestedNav": [
                {
                    "listType": "TEXT_ONLY",
                    "title": "shop by product",
                    "routes": {
                        "men": [
                            {
                                "label": "View All",
                                "query": "all"
                            },
                            {
                                "label": "New In",
                                "query": "new-in"
                            },
                            {
                                "label": "Jackets & Coats",
                                "query": "coats,jackets"
                            },
                            {
                                "label": "Jumpers & Cardigans",
                                "query": "jumpers,cardigans"
                            },
                            {
                                "label": "Shirts",
                                "query": "shirts"
                            },
                            {
                                "label": "Jeans",
                                "query": "jeans"
                            },
                            {
                                "label": "T-Shirts & Vests",
                                "query": "vests,t-shirts"
                            },
                            {
                                "label": "Hoodies & Sweatshirts",
                                "query": "hoodies,sweatshirts"
                            },
                            {
                                "label": "Co-Ords",
                                "query": "co-ords"
                            },
                            {
                                "label": "Designer",
                                "query": "designer"
                            },
                            {
                                "label": "Joggers",
                                "query": "joggers"
                            },
                            {
                                "label": "Loungewear",
                                "query": "loungewears"
                            },
                            {
                                "label": "Multipacks",
                                "query": "multipacks"
                            },
                            {
                                "label": "Polo Shirts",
                                "query": "polo-shirts"
                            },
                            {
                                "label": "Shorts",
                                "query": "shorts"
                            },
                            {
                                "label": "Sportswear",
                                "query": "sportswear"
                            },
                            {
                                "label": "Suits & Tailoring",
                                "query": "suits,tailoring"
                            },
                            {
                                "label": "Swimwear",
                                "query": "swimwears,beachwears"
                            },
                            {
                                "label": "Tracksuits",
                                "query": "tracksuits"
                            },
                            {
                                "label": "Trousers & Chinos",
                                "query": "chinos,trousers"
                            }
                        ],
                        "women": [
                            {
                                "label": "New In",
                                "query": "new-in"
                            },
                            {
                                "label": "View All",
                                "query": "all"
                            },
                            {
                                "label": "Coats & Jackets",
                                "query": "coats,jackets"
                            },
                            {
                                "label": "Jumpers & Cardigans",
                                "query": "jumpers,cardigans"
                            },
                            {
                                "label": "Dresses",
                                "query": "dresses"
                            },
                            {
                                "label": "Lingerie & Nightwear",
                                "query": "lingerie,nightwears"
                            },
                            {
                                "label": "Tracksuits & Joggers",
                                "query": "tracksuits,joggers"
                            },
                            {
                                "label": "Tops",
                                "query": "tops"
                            },
                            {
                                "label": "Blazers",
                                "query": "blazers"
                            },
                            {
                                "label": "Cargo Trousers",
                                "query": "cargo-trousers"
                            },
                            {
                                "label": "Co-Ords",
                                "query": "co-ords"
                            },
                            {
                                "label": "Designer",
                                "query": "designer"
                            },
                            {
                                "label": "Exclusive at ASOS",
                                "query": "asos"
                            },
                            {
                                "label": "Hoodies & Sweatshirts",
                                "query": "hoodies,sweatshirts"
                            },
                            {
                                "label": "Jeans",
                                "query": "jeans"
                            },
                            {
                                "label": "Jumpsuits & Playsuits",
                                "query": "jumpsuits,playsuits"
                            },
                            {
                                "label": "Loungewear",
                                "query": "loungewears"
                            },
                            {
                                "label": "Multipacks",
                                "query": "multipacks"
                            },
                            {
                                "label": "Shirts & Blouses",
                                "query": "shirts,blouses"
                            },
                            {
                                "label": "Shorts",
                                "query": "shorts"
                            },
                            {
                                "label": "Skirts",
                                "query": "skirts"
                            },
                            {
                                "label": "Sportswear",
                                "query": "sportswear"
                            },
                            {
                                "label": "Suits & Tailoring",
                                "query": "suits,tailoring"
                            },
                            {
                                "label": "Swimwear & Beachwear",
                                "query": "swimwears,beachwears"
                            },
                            {
                                "label": "Trousers & Leggings",
                                "query": "trousers,leggings"
                            }
                        ]
                    }
                },
                {
                    "listType": "ROUNDED_FIG_Y",
                    "title": "shop by body fit",
                    "routes": {
                        "men": [
                            {
                                "fig": "/assets/nav/men/men-clothing__plus-size.webp",
                                "label": "Plus Size",
                                "query": "plus-size"
                            },
                            {
                                "fig": "/assets/nav/men/men-clothing__tall.webp",
                                "label": "Tall",
                                "query": "tall"
                            }
                        ],
                        "women": [
                            {
                                "fig": "/assets/nav/women/women-clothing__curve-and-plus-size.webp",
                                "label": "curve & Plus Size",
                                "query": "plus-size,curve"
                            },
                            {
                                "fig": "/assets/nav/women/women-clothing__maternity.webp",
                                "label": "maternity",
                                "query": "maternity"
                            },
                            {
                                "fig": "/assets/nav/women/women-clothing__petite.webp",
                                "label": "petite",
                                "query": "petite"
                            },
                            {
                                "fig": "/assets/nav/women/women-clothing__tall.webp",
                                "label": "tall",
                                "query": "tall"
                            }
                        ]
                    }
                },
                {
                    "listType": "ROUNDED_FIG_X",
                    "title": "shop by edit",
                    "routes": {
                        "men": [
                            {
                                "fig": "/assets/nav/men/men-clothing__holiday.webp",
                                "label": "Holiday",
                                "query": "holiday"
                            },
                            {
                                "fig": "/assets/nav/men/men-clothing__asos-basics.webp",
                                "label": "ASOS Basics",
                                "query": "asos"
                            },
                            {
                                "fig": "/assets/nav/men/men-clothing__festival.webp",
                                "label": "Festival",
                                "query": "festival"
                            },
                            {
                                "fig": "/assets/nav/men/men-clothing__partywear.webp",
                                "label": "Partywear",
                                "query": "partywears,party"
                            },
                            {
                                "fig": "/assets/nav/men/men-clothing__linen-looks.webp",
                                "label": "Linen looks",
                                "query": "linen-looks"
                            },
                            {
                                "fig": "/assets/nav/men/men-clothing__wedding.webp",
                                "label": "Wedding",
                                "query": "wedding"
                            }
                        ],
                        "women": [
                            {
                                "fig": "/assets/nav/women/women-clothing__holiday.webp",
                                "label": "Holiday",
                                "query": "holiday"
                            },
                            {
                                "fig": "/assets/nav/women/women-clothing__modest-fashion.webp",
                                "label": "Modest Fashion",
                                "query": "modest-fashion"
                            },
                            {
                                "fig": "/assets/nav/women/women-clothing__linen-looks.webp",
                                "label": "Linen Looks",
                                "query": "linen-looks"
                            },
                            {
                                "fig": "/assets/nav/women/women-clothing__ski-and-snowboard.webp",
                                "label": "Ski & Snowboard",
                                "query": "ski,snowboard"
                            }
                        ]
                    }
                }
            ]
        },
        {
            "label": "dresses",
            "query": "dresses",
            "nestedNav": [
                {
                    "listType": "TEXT_ONLY",
                    "title": "shop by type",
                    "routes": {
                        "men": [],
                        "women": [
                            {
                                "label": "View All",
                                "query": "all"
                            },
                            {
                                "label": "New In",
                                "query": "new-in"
                            },
                            {
                                "label": "Evening Dresses",
                                "query": "evening-dresses"
                            },
                            {
                                "label": "Wedding Guest Dresses",
                                "query": "wedding-guest"
                            },
                            {
                                "label": "Day Dresses",
                                "query": "day-dresses"
                            },
                            {
                                "label": "Bridesmaid Dresses",
                                "query": "bridesmaid-dresses"
                            },
                            {
                                "label": "Party Dresses",
                                "query": "party-dresses"
                            }
                        ]
                    }
                },
                {
                    "listType": "ROUNDED_FIG_X",
                    "title": "trending now",
                    "routes": {
                        "men": [],
                        "women": [
                            {
                                "fig": "/assets/nav/women/women-dresses__white-dresses.webp",
                                "label": "White Dresses",
                                "query": "white-dresses"
                            },
                            {
                                "fig": "/assets/nav/women/women-dresses__slip-dresses.webp",
                                "label": "Slip Dresses",
                                "query": "slip-dresses"
                            },
                            {
                                "fig": "/assets/nav/women/women-dresses__workwear-dresses.webp",
                                "label": "Workwear Dresses",
                                "query": "workwear-dresses"
                            },
                            {
                                "fig": "/assets/nav/women/women-dresses__lbds.webp",
                                "label": "LBDs",
                                "query": "lbds"
                            },
                            {
                                "fig": "/assets/nav/women/women-dresses__jumper-dresses.webp",
                                "label": "Jumper Dresses",
                                "query": "jumper-dresses"
                            }
                        ]
                    }
                },
                {
                    "listType": "ROUNDED_FIG_Y",
                    "title": "shop by body fit",
                    "routes": {
                        "men": [],
                        "women": [
                            {
                                "fig": "/assets/nav/women/women-dresses__curve-and-plus-size.webp",
                                "label": "Curve & Plus Size",
                                "query": "plus-size,curve"
                            },
                            {
                                "fig": "/assets/nav/women/women-dresses__maternity.webp",
                                "label": "Maternity",
                                "query": "maternity"
                            },
                            {
                                "fig": "/assets/nav/women/women-dresses__petite.webp",
                                "label": "Petite",
                                "query": "petite"
                            },
                            {
                                "fig": "/assets/nav/women/women-dresses__tall.webp",
                                "label": "Tall",
                                "query": "tall"
                            }
                        ]
                    }
                },
                {
                    "listType": "FIG_ONLY",
                    "title": "",
                    "routes": {
                        "men": [],
                        "women": [
                            {
                                "fig": "/assets/nav/women/women-dresses__asos-design.webp",
                                "label": "asos design",
                                "query": "asos"
                            },
                            {
                                "fig": "/assets/nav/women/women-dresses__topshop.webp",
                                "label": "topshop",
                                "query": "topshop"
                            },
                            {
                                "fig": "/assets/nav/women/women-dresses__asos-luxe.webp",
                                "label": "asos luxe",
                                "query": "asos edition"
                            }
                        ]
                    }
                }
            ]
        },
        {
            "label": "shoes",
            "query": "shoes",
            "nestedNav": [
                {
                    "listType": "TEXT_ONLY",
                    "title": "shop by product",
                    "routes": {
                        "men": [
                            {
                                "label": "view all",
                                "query": "all"
                            },
                            {
                                "label": "new-in",
                                "query": ""
                            },
                            {
                                "label": "trainers",
                                "query": ""
                            },
                            {
                                "label": "boots",
                                "query": ""
                            },
                            {
                                "label": "loafers",
                                "query": ""
                            },
                            {
                                "label": "sandals",
                                "query": ""
                            },
                            {
                                "label": "shoes",
                                "query": ""
                            },
                            {
                                "label": "sliders & Flip flops",
                                "query": ""
                            },
                            {
                                "label": "slippers",
                                "query": ""
                            },
                            {
                                "label": "smart shoes",
                                "query": ""
                            },
                            {
                                "label": "sports trainers",
                                "query": ""
                            }
                        ],
                        "women": [
                            {
                                "label": "view all",
                                "query": "all"
                            },
                            {
                                "label": "new-in",
                                "query": ""
                            },
                            {
                                "label": "trainers",
                                "query": ""
                            },
                            {
                                "label": "boots",
                                "query": ""
                            },
                            {
                                "label": "heels",
                                "query": ""
                            },
                            {
                                "label": "sandals",
                                "query": ""
                            },
                            {
                                "label": "flat shoes",
                                "query": ""
                            },
                            {
                                "label": "loafers",
                                "query": ""
                            },
                            {
                                "label": "running Trainers",
                                "query": ""
                            },
                            {
                                "label": "sliders & Flip flops",
                                "query": ""
                            }
                        ]
                    }
                },
                {
                    "listType": "ROUNDED_FIG_X",
                    "title": "shop by brand",
                    "routes": {
                        "men": [
                            {
                                "fig": "/assets/nav/men/men-shoes__asos-design.webp",
                                "label": "ASOS DESIGN",
                                "query": ""
                            },
                            {
                                "fig": "/assets/nav/men/men-shoes__adidas.webp",
                                "label": "adidas Originals",
                                "query": ""
                            },
                            {
                                "fig": "/assets/nav/men/men-shoes__converse.webp",
                                "label": "converse",
                                "query": ""
                            },
                            {
                                "fig": "/assets/nav/men/men-shoes__new-balance.webp",
                                "label": "New Balance",
                                "query": ""
                            },
                            {
                                "fig": "/assets/nav/men/men-shoes__nike.webp",
                                "label": "nike",
                                "query": ""
                            },
                            {
                                "fig": "/assets/nav/men/men-shoes__puma.webp",
                                "label": "puma",
                                "query": ""
                            }
                        ],
                        "women": [
                            {
                                "fig": "/assets/nav/women/women-shoes__asos-design.webp",
                                "label": "asos design",
                                "query": ""
                            },
                            {
                                "fig": "/assets/nav/women/women-shoes__dr-martens.webp",
                                "label": "Dr Martens",
                                "query": ""
                            },
                            {
                                "fig": "/assets/nav/women/women-shoes__public-desire.webp",
                                "label": "Public Desire",
                                "query": ""
                            },
                            {
                                "fig": "/assets/nav/women/women-shoes__aldo.webp",
                                "label": "Aldo",
                                "query": ""
                            },
                            {
                                "fig": "/assets/nav/women/women-shoes__converse.webp",
                                "label": "Converse",
                                "query": ""
                            },
                            {
                                "fig": "/assets/nav/women/women-shoes__nike.webp",
                                "label": "nike",
                                "query": ""
                            }
                        ]
                    }
                },
                {
                    "listType": "TEXT_ONLY",
                    "title": "shop by trainer style",
                    "routes": {
                        "men": [
                            {
                                "label": "adidas stan smith",
                                "query": ""
                            },
                            {
                                "label": "nike air  max",
                                "query": ""
                            },
                            {
                                "label": "new balance 574",
                                "query": ""
                            },
                            {
                                "label": "vans old skool",
                                "query": ""
                            },
                            {
                                "label": "converse all star",
                                "query": ""
                            },
                            {
                                "label": "nike air force 1",
                                "query": ""
                            },
                            {
                                "label": "new balance 530",
                                "query": ""
                            },
                            {
                                "label": "adidas gazelle",
                                "query": ""
                            },
                            {
                                "label": "reebok classic",
                                "query": ""
                            }
                        ],
                        "women": [
                            {
                                "label": "nike air max",
                                "query": ""
                            },
                            {
                                "label": "adidas stan smith",
                                "query": ""
                            },
                            {
                                "label": "new balance 530",
                                "query": ""
                            },
                            {
                                "label": "puma cali",
                                "query": ""
                            },
                            {
                                "label": "vans old skool",
                                "query": ""
                            },
                            {
                                "label": "converse all star",
                                "query": ""
                            },
                            {
                                "label": "adidas gazelle",
                                "query": ""
                            },
                            {
                                "label": "reebok classic",
                                "query": ""
                            }
                        ]
                    }
                },
                {
                    "listType": "FIG_ONLY",
                    "title": "",
                    "routes": {
                        "men": [
                            {
                                "fig": "/assets/nav/men/men-shoes__white-trainers.webp",
                                "label": "white trainers",
                                "query": ""
                            },
                            {
                                "fig": "/assets/nav/men/men-shoes__chunky-trainers.webp",
                                "label": "chunky trainers",
                                "query": ""
                            },
                            {
                                "fig": "/assets/nav/men/men-shoes__hi-tops.webp",
                                "label": "HI-TOPS",
                                "query": ""
                            }
                        ],
                        "women": [
                            {
                                "fig": "/assets/nav/women/women-shoes__white-trainers.webp",
                                "label": "white trainers",
                                "query": ""
                            },
                            {
                                "fig": "/assets/nav/women/women-shoes__chunky-trainers.webp",
                                "label": "chunky trainers",
                                "query": ""
                            },
                            {
                                "fig": "/assets/nav/women/women-shoes__hi-tops.webp",
                                "label": "HI-TOPS",
                                "query": ""
                            }
                        ]
                    }
                }
            ]
        },
        {
            "label": "sportswear",
            "query": "sportswear",
            "nestedNav": [
                {
                    "listType": "TEXT_ONLY",
                    "title": "shop by product",
                    "routes": {
                        "men": [
                            {
                                "label": "View All",
                                "query": "all"
                            },
                            {
                                "label": "New In",
                                "query": "new-in"
                            },
                            {
                                "label": "Trainers",
                                "query": "trainers"
                            },
                            {
                                "label": "Shorts",
                                "query": "shorts"
                            },
                            {
                                "label": "Tops",
                                "query": "tops"
                            },
                            {
                                "label": "Hoodies & Sweatshirts",
                                "query": "hoodies,sweatshirts"
                            },
                            {
                                "label": "Jackets",
                                "query": "jackets"
                            },
                            {
                                "label": "Jaggers",
                                "query": "joggers"
                            },
                            {
                                "label": "Trousers & Tights",
                                "query": "tights,trousers"
                            }
                        ],
                        "women": [
                            {
                                "label": "View All",
                                "query": "all"
                            },
                            {
                                "label": "New In",
                                "query": "new-in"
                            },
                            {
                                "label": "Trainers",
                                "query": "trainers"
                            },
                            {
                                "label": "Leggings",
                                "query": "leggings"
                            },
                            {
                                "label": "Tops",
                                "query": "tops"
                            },
                            {
                                "label": "Hoodies & Sweatshirts",
                                "query": "hoodies,sweatshirts"
                            },
                            {
                                "label": "Jackets",
                                "query": "jackets"
                            },
                            {
                                "label": "Shorts",
                                "query": "shorts"
                            },
                            {
                                "label": "Sports Bras",
                                "query": "sports-bras"
                            }
                        ]
                    }
                },
                {
                    "listType": "ROUNDED_FIG_X",
                    "title": "shop by activity",
                    "routes": {
                        "men": [
                            {
                                "fig": "/assets/nav/men/men-sportswear__ski-and-snowboard.webp",
                                "label": "Ski & Snowboard",
                                "query": "ski-and-snowboard,ski,snowboard"
                            },
                            {
                                "fig": "/assets/nav/men/men-sportswear__gym-and-training.webp",
                                "label": "Gym & Training",
                                "query": "gym-and-training,training,gym"
                            },
                            {
                                "fig": "/assets/nav/men/men-sportswear__football.webp",
                                "label": "Football",
                                "query": "football"
                            },
                            {
                                "fig": "/assets/nav/men/men-sportswear__lifestyle.webp",
                                "label": "Lifestyle",
                                "query": "lifestyle"
                            },
                            {
                                "fig": "/assets/nav/men/men-sportswear__outdoors.webp",
                                "label": "Outdoors",
                                "query": "outdoors"
                            },
                            {
                                "fig": "/assets/nav/men/men-sportswear__running.webp",
                                "label": "Running",
                                "query": "running"
                            }
                        ],
                        "women": [
                            {
                                "fig": "/assets/nav/women/women-sportswear__ski-and-snowboard.webp",
                                "label": "Ski & Snowboard",
                                "query": "ski-and-snowboard,ski,snowboard"
                            },
                            {
                                "fig": "/assets/nav/women/women-sportswear__gym-and-training.webp",
                                "label": "Gym & Training",
                                "query": "gym-and-training,training,gym"
                            },
                            {
                                "fig": "/assets/nav/women/women-sportswear__lifestyle.webp",
                                "label": "Lifestyle",
                                "query": "lifestyle"
                            },
                            {
                                "fig": "/assets/nav/women/women-sportswear__outdoors.webp",
                                "label": "Outdoors",
                                "query": "outdoors"
                            },
                            {
                                "fig": "/assets/nav/women/women-sportswear__running.webp",
                                "label": "Running",
                                "query": "running"
                            },
                            {
                                "fig": "/assets/nav/women/women-sportswear__yoga-and-studio.webp",
                                "label": "Yoga & Studio",
                                "query": "yoga,studio"
                            }
                        ]
                    }
                },
                {
                    "listType": "ROUNDED_FIG_X",
                    "title": "shop by brand",
                    "routes": {
                        "men": [
                            {
                                "fig": "/assets/nav/men/men-sportswear__adidas.webp",
                                "label": "Adidas",
                                "query": "adidas"
                            },
                            {
                                "fig": "/assets/nav/men/men-sportswear__asos-4505.webp",
                                "label": "ASOS 4505",
                                "query": "asos 4505,asos edition"
                            },
                            {
                                "fig": "/assets/nav/men/men-sportswear__converse.webp",
                                "label": "Converse",
                                "query": "converse"
                            },
                            {
                                "fig": "/assets/nav/men/men-sportswear__new-balance.webp",
                                "label": "New Balance",
                                "query": "new balance"
                            },
                            {
                                "fig": "/assets/nav/men/men-sportswear__nike.webp",
                                "label": "Nike",
                                "query": "nike"
                            },
                            {
                                "fig": "/assets/nav/men/men-sportswear__the-north-face.webp",
                                "label": "The North Face",
                                "query": "the north face"
                            }
                        ],
                        "women": [
                            {
                                "fig": "/assets/nav/women/women-sportswear__adidas.webp",
                                "label": "Adidas",
                                "query": "adidas"
                            },
                            {
                                "fig": "/assets/nav/women/women-sportswear__asos-4505.webp",
                                "label": "ASOS 4505",
                                "query": "asos 4505,asos edition"
                            },
                            {
                                "fig": "/assets/nav/women/women-sportswear__converse.webp",
                                "label": "Converse",
                                "query": "converse"
                            },
                            {
                                "fig": "/assets/nav/women/women-sportswear__new-balance-2.webp",
                                "label": "New Balance",
                                "query": "new balance"
                            },
                            {
                                "fig": "/assets/nav/women/women-sportswear__nike.webp",
                                "label": "Nike",
                                "query": "nike"
                            },
                            {
                                "fig": "/assets/nav/women/women-sportswear__the-north-face.webp",
                                "label": "The North Face",
                                "query": "the north face"
                            }
                        ]
                    }
                },
                {
                    "listType": "FIG_ONLY",
                    "title": "",
                    "routes": {
                        "men": [
                            {
                                "fig": "/assets/nav/men/men-sportswear__running-fig-only.webp",
                                "label": "Running",
                                "query": "running"
                            },
                            {
                                "fig": "/assets/nav/men/men-sportswear__new-balance-fig-only.webp",
                                "label": "New Balance",
                                "query": "new balance"
                            },
                            {
                                "fig": "/assets/nav/men/men-sportswear__outdoors-fig-only.webp",
                                "label": "Outdoors",
                                "query": "outdoors"
                            }
                        ],
                        "women": [
                            {
                                "fig": "/assets/nav/women/women-sportswear__bestselling-trainers.webp",
                                "label": "Bestselling Trainers",
                                "query": "trainers"
                            },
                            {
                                "fig": "/assets/nav/women/women-sportswear__outdoors-2.webp",
                                "label": "Outdoors",
                                "query": "outdoors"
                            },
                            {
                                "fig": "/assets/nav/women/women-sportswear__new-balance.webp",
                                "label": "New Balance",
                                "query": "new balance"
                            }
                        ]
                    }
                }
            ]
        },
        {
            "label": "jeans",
            "query": "jeans",
            "nestedNav": [
                {
                    "listType": "TEXT_ONLY",
                    "title": "shop by style",
                    "routes": {
                        "men": [
                            {
                                "label": "View All",
                                "query": "all"
                            },
                            {
                                "label": "Straight Jeans",
                                "query": "straight-jeans"
                            },
                            {
                                "label": "Wide Jeans",
                                "query": "wide-jeans"
                            },
                            {
                                "label": "Skinny Jeans",
                                "query": "skinny-jeans"
                            },
                            {
                                "label": "Tapered Jeans",
                                "query": "tapered-jeans"
                            },
                            {
                                "label": "Ripped Jeans",
                                "query": "ripped-jeans"
                            },
                            {
                                "label": "Slim Jeans",
                                "query": "slim-jeans"
                            }
                        ],
                        "women": [
                            {
                                "label": "View All",
                                "query": "all"
                            },
                            {
                                "label": "Mom Jeans",
                                "query": "mom-jeans"
                            },
                            {
                                "label": "Straight Leg Jeans",
                                "query": "straight-leg-jeans"
                            },
                            {
                                "label": "Wide Leg Jeans",
                                "query": "wide-leg-jeans"
                            },
                            {
                                "label": "Skinny Jeans",
                                "query": "skinny-jeans"
                            },
                            {
                                "label": "Ripped Jeans",
                                "query": "ripped-jeans"
                            },
                            {
                                "label": "Slim Jeans",
                                "query": "slim-jeans"
                            }
                        ]
                    }
                },
                {
                    "listType": "ROUNDED_FIG_Y",
                    "title": "shop by body fit",
                    "routes": {
                        "men": [
                            {
                                "fig": "/assets/nav/men/men-jeans__tall.webp",
                                "label": "Tall",
                                "query": "tall"
                            },
                            {
                                "fig": "/assets/nav/men/men-jeans__plus.webp",
                                "label": "Plus",
                                "query": "plus-size"
                            }
                        ],
                        "women": [
                            {
                                "fig": "/assets/nav/women/women-jeans__curve-and-plus-size.webp",
                                "label": "Curve & Plus Size",
                                "query": "plus-size,curve"
                            },
                            {
                                "fig": "/assets/nav/women/women-jeans__petite.webp",
                                "label": "Petite",
                                "query": "petite"
                            },
                            {
                                "fig": "/assets/nav/women/women-jeans__maternity.webp",
                                "label": "Maternity",
                                "query": "maternity"
                            },
                            {
                                "fig": "/assets/nav/women/women-jeans__tall.webp",
                                "label": "Tall",
                                "query": "tall"
                            }
                        ]
                    }
                },
                {
                    "listType": "ROUNDED_FIG_X",
                    "title": "shop by colour",
                    "routes": {
                        "men": [
                            {
                                "fig": "/assets/nav/men/men-jeans__black-jeans.webp",
                                "label": "Black Jeans",
                                "query": "black-jeans"
                            },
                            {
                                "fig": "/assets/nav/men/men-jeans__blue-jeans.webp",
                                "label": "Blue Jeans",
                                "query": "blue-jeans"
                            },
                            {
                                "fig": "/assets/nav/men/men-jeans__grey-jeans.webp",
                                "label": "Grey Jeans",
                                "query": "grey-jeans"
                            },
                            {
                                "fig": "/assets/nav/men/men-jeans__white-jeans.webp",
                                "label": "White Jeans",
                                "query": "white-jeans"
                            }
                        ],
                        "women": [
                            {
                                "fig": "/assets/nav/women/women-jeans__black-jeans.webp",
                                "label": "Black Jeans",
                                "query": "black-jeans"
                            },
                            {
                                "fig": "/assets/nav/women/women-jeans__blue-jeans.webp",
                                "label": "Blue Jeans",
                                "query": "blue-jeans"
                            },
                            {
                                "fig": "/assets/nav/women/women-jeans__grey-jeans.webp",
                                "label": "Grey Jeans",
                                "query": "grey-jeans"
                            },
                            {
                                "fig": "/assets/nav/women/women-jeans__white-jeans.webp",
                                "label": "White Jeans",
                                "query": "white-jeans"
                            }
                        ]
                    }
                },
                {
                    "listType": "ROUNDED_FIG_X",
                    "title": "shop by brand",
                    "routes": {
                        "men": [
                            {
                                "fig": "/assets/nav/men/men-jeans__asos-design.webp",
                                "label": "ASOS DESIGN",
                                "query": "asos"
                            },
                            {
                                "fig": "/assets/nav/men/men-jeans__topman.webp",
                                "label": "Topman",
                                "query": "topman"
                            },
                            {
                                "fig": "/assets/nav/men/men-jeans__pull-and-bear.webp",
                                "label": "Pull&Bear",
                                "query": "pull_bear"
                            },
                            {
                                "fig": "/assets/nav/men/men-jeans__levis.webp",
                                "label": "Levi's",
                                "query": "levis's"
                            },
                            {
                                "fig": "/assets/nav/men/men-jeans__jack-and-jones.webp",
                                "label": "Jack & Jones",
                                "query": "jack_jones"
                            },
                            {
                                "fig": "/assets/nav/men/men-jeans__only-and-sons.webp",
                                "label": "Only & Sons",
                                "query": "only_sons"
                            }
                        ],
                        "women": [
                            {
                                "fig": "/assets/nav/women/women-jeans__asos-design.webp",
                                "label": "ASOS DESIGN",
                                "query": "asos"
                            },
                            {
                                "fig": "/assets/nav/women/women-jeans__topshop.webp",
                                "label": "topshop",
                                "query": "topshop"
                            },
                            {
                                "fig": "/assets/nav/women/women-jeans__stradivarius.webp",
                                "label": "stradivarius",
                                "query": "stradivarius"
                            },
                            {
                                "fig": "/assets/nav/women/women-jeans__levis.webp",
                                "label": "Levi's",
                                "query": "levi's"
                            },
                            {
                                "fig": "/assets/nav/women/women-jeans__river-island.webp",
                                "label": "River Island",
                                "query": "river island"
                            }
                        ]
                    }
                }
            ]
        },
        {
            "label": "brands",
            "query": "brands",
            "nestedNav": [
                {
                    "listType": "TEXT_ONLY",
                    "title": "top brands",
                    "routes": {
                        "men": [
                            {
                                "label": "Adidas",
                                "query": "adidas"
                            },
                            {
                                "label": "Bershka",
                                "query": "bershka"
                            },
                            {
                                "label": "New Balance",
                                "query": "new balance"
                            },
                            {
                                "label": "New Look",
                                "query": "new look"
                            },
                            {
                                "label": "Nike",
                                "query": "nike"
                            },
                            {
                                "label": "Pull&Bear",
                                "query": "pull_bear"
                            },
                            {
                                "label": "Puma",
                                "query": "puma"
                            },
                            {
                                "label": "River Island",
                                "query": "river island"
                            },
                            {
                                "label": "The North Face",
                                "query": "the north face"
                            },
                            {
                                "label": "Tommy Hilfiger",
                                "query": "tommy hilfiger"
                            },
                            {
                                "label": "Jack & Jones",
                                "query": "jack_jones"
                            }
                        ],
                        "women": [
                            {
                                "label": "Adidas",
                                "query": "adidas"
                            },
                            {
                                "label": "Bershka",
                                "query": "bershka"
                            },
                            {
                                "label": "New Balance",
                                "query": "new balance"
                            },
                            {
                                "label": "New Look",
                                "query": "new look"
                            },
                            {
                                "label": "Nike",
                                "query": "nike"
                            },
                            {
                                "label": "& Other Stories",
                                "query": "other stories"
                            },
                            {
                                "label": "Puma",
                                "query": "puma"
                            },
                            {
                                "label": "River Island",
                                "query": "river island"
                            },
                            {
                                "label": "The North Face",
                                "query": "the north face"
                            },
                            {
                                "label": "Tommy Hilfiger",
                                "query": "tommy hilfiger"
                            }
                        ]
                    }
                },
                {
                    "listType": "ROUNDED_FIG_X",
                    "title": "asos brands",
                    "routes": {
                        "men": [
                            {
                                "fig": "/assets/nav/men/men-brands__view-all.webp",
                                "label": "View All",
                                "query": "all"
                            },
                            {
                                "fig": "/assets/nav/men/men-brands__asos-design.webp",
                                "label": "ASOS DESIGN",
                                "query": "asos"
                            },
                            {
                                "fig": "/assets/nav/men/men-brands__asos-4505.webp",
                                "label": "ASOS 4505",
                                "query": "asos 4505"
                            },
                            {
                                "fig": "/assets/nav/men/men-brands__topman.webp",
                                "label": "Topman",
                                "query": "topman"
                            },
                            {
                                "fig": "/assets/nav/men/men-brands__collusion.webp",
                                "label": "COLLUSION",
                                "query": "collusion"
                            },
                            {
                                "fig": "/assets/nav/men/men-brands__reclaimed-vintage.webp",
                                "label": "ReclaimedVintage",
                                "query": "reclaimed vintage"
                            }
                        ],
                        "women": [
                            {
                                "fig": "/assets/nav/women/women-brands__view-all.webp",
                                "label": "View All",
                                "query": "all"
                            },
                            {
                                "fig": "/assets/nav/women/women-brands__asos-design.webp",
                                "label": "ASOS DESIGN",
                                "query": "asos"
                            },
                            {
                                "fig": "/assets/nav/women/women-brands__topshop.webp",
                                "label": "Topshop",
                                "query": "topshop"
                            },
                            {
                                "fig": "/assets/nav/women/women-brands__collusion.webp",
                                "label": "COLLUSION",
                                "query": "collusion"
                            },
                            {
                                "fig": "/assets/nav/women/women-brands__miss-selfridge.webp",
                                "label": "Miss Selfridge",
                                "query": "miss selfridge"
                            },
                            {
                                "fig": "/assets/nav/women/women-brands__asos-4505.webp",
                                "label": "ASOS 4505",
                                "query": "asos 4505"
                            }
                        ]
                    }
                },
                {
                    "listType": "ROUNDED_FIG_X",
                    "title": "discover brands",
                    "routes": {
                        "men": [
                            {
                                "fig": "/assets/nav/men/men-brands__new-in-2.webp",
                                "label": "New In",
                                "query": "new-in"
                            },
                            {
                                "fig": "/assets/nav/men/men-brands__outdoors.webp",
                                "label": "Outdoors",
                                "query": "outdoors"
                            },
                            {
                                "fig": "/assets/nav/men/men-brands__streetwear.webp",
                                "label": "Streetwear",
                                "query": "streetwears"
                            },
                            {
                                "fig": "/assets/nav/men/men-brands__trainers.webp",
                                "label": "Trainers",
                                "query": "trainers"
                            },
                            {
                                "fig": "/assets/nav/men/men-brands__emerging-brands.webp",
                                "label": "Emerging Brands",
                                "query": "emerging-brands"
                            }
                        ],
                        "women": [
                            {
                                "fig": "/assets/nav/women/women-brands__new-in.webp",
                                "label": "New In",
                                "query": "new-in"
                            },
                            {
                                "fig": "/assets/nav/women/women-brands__outdoor.webp",
                                "label": "Outdoor",
                                "query": "outdoors"
                            },
                            {
                                "fig": "/assets/nav/women/women-brands__streetwear.webp",
                                "label": "Streetwear",
                                "query": "streetwears"
                            },
                            {
                                "fig": "/assets/nav/women/women-brands__trainers.webp",
                                "label": "Trainers",
                                "query": "trainers"
                            },
                            {
                                "fig": "/assets/nav/women/women-brands__emerging-brands.webp",
                                "label": "Emerging Brands",
                                "query": "emerging-brands"
                            }
                        ]
                    }
                },
                {
                    "listType": "FIG_ONLY",
                    "title": "discover",
                    "routes": {
                        "men": [
                            {
                                "fig": "/assets/nav/men/men-brands__plus-size-brands.webp",
                                "label": "Plus Size Brands",
                                "query": "plus-size,brands"
                            },
                            {
                                "fig": "/assets/nav/men/men-brands__asos-brands.webp",
                                "label": "ASOS BRANDS",
                                "query": "asos,asos edition,asos 4505"
                            }
                        ],
                        "women": [
                            {
                                "fig": "/assets/nav/women/women-brands__curve-and-plus-size.webp",
                                "label": "Curve & Plus Size",
                                "query": "plus-size,curve"
                            },
                            {
                                "fig": "/assets/nav/women/women-brands__asos-brands.webp",
                                "label": "ASOS BRANDS",
                                "query": "asos,asos edition,asos 4505"
                            }
                        ]
                    }
                }
            ]
        }
    ]
}